sorterpy/__init__.py
sorterpy/sorterpy.py
sorterpy-0.3.2.dist-info/licenses/LICENSE
sorterpy-0.3.2.dist-info/METADATA
sorterpy-0.3.2.dist-info/WHEEL
sorterpy-0.3.2.dist-info/top_level.txt
sorterpy-0.3.2.dist-info/RECORD
