Metadata-Version: 2.4
Name: sorterpy
Version: 0.3.2
Summary: the official Python SDK for sorter.social's seamless data labeling solutions for any AI/ML workflow.
Author-email: Jason McElhenney <jason@sorter.social>
Maintainer-email: Jason McElhenney <jason@sorter.social>
License: MIT license
Project-URL: bugs, https://github.com/sorterisntonline/sorterpy/issues
Project-URL: changelog, https://github.com/sorterisntonline/sorterpy/blob/master/changelog.md
Project-URL: homepage, https://github.com/sorterisntonline/sorterpy
License-File: LICENSE
Requires-Dist: httpx
Requires-Dist: loguru
Requires-Dist: python-dotenv
Provides-Extra: dev
Requires-Dist: coverage; extra == "dev"
Requires-Dist: mypy; extra == "dev"
Requires-Dist: pytest; extra == "dev"
Requires-Dist: ruff; extra == "dev"
Dynamic: license-file
